kink/__init__.py
kink/__verstion__.py
kink/container.py
kink/inject.py
kink/package_scanning.py
kink/py.typed
kink/typing_support.py
kink/errors/__init__.py
kink/errors/container_error.py
kink/errors/execution_error.py
kink/errors/resolver_error.py
kink/errors/service_error.py
turintech_ioc-2.0.0.dist-info/METADATA
turintech_ioc-2.0.0.dist-info/WHEEL
turintech_ioc-2.0.0.dist-info/RECORD
