Metadata-Version: 2.4
Name: turintech-ioc
Version: 2.0.0
Summary: Inversion of control implementation
Requires-Python: <3.14,>=3.8
Requires-Dist: loguru<1.0.0,>0.7.0
Requires-Dist: typing-extensions<5.0.0,>=4.5.0
